supernano/__init__.py
supernano/install.py
supernano/main.py
SuperNano-2.2.1.dist-info/METADATA
SuperNano-2.2.1.dist-info/WHEEL
SuperNano-2.2.1.dist-info/entry_points.txt
SuperNano-2.2.1.dist-info/top_level.txt
SuperNano-2.2.1.dist-info/RECORD
