Metadata-Version: 2.1
Name: SuperNano
Version: 2.2.1
Summary: A console-based text editor.
Home-page: https://github.com/LcfherShell/SuperNano
Author: LcfherShell
Author-email: alfiandecker2@gmail.com
Classifier: Programming Language :: Python :: 3
Classifier: License :: OSI Approved :: MIT License
Classifier: Operating System :: OS Independent
Requires-Python: >=3.6
